{
  "session_id": "192579c9-2a77-4f09-9fdc-4475964f6114",
  "status": "COMPLETE",
  "completion_percentage": 100,
  "current_batch": 1211,
  "total_expansions": 269,
  "thin_pages_remaining": 0,
  "last_build": {
    "pages": 434,
    "time_seconds": 93.81,
    "errors": 0,
    "status": "Complete"
  },
  "final_expansions": [
    {
      "file": "best-ai-website-builders-speed.astro",
      "before": 1092,
      "after": 1159,
      "added": 67
    },
    {
      "file": "ai-website-builders-for-saas-startups-detailed-v2.astro",
      "before": 1092,
      "after": 1134,
      "added": 42
    },
    {
      "file": "best-ai-website-builder-for-book-authors.astro",
      "before": 1097,
      "after": 1156,
      "added": 59
    },
    {
      "file": "framer-vs-webflow.astro",
      "before": 1097,
      "after": 1171,
      "added": 74
    }
  ],
  "timestamp": "2026-01-31T04:32:00Z"
}
